scNET/KNNDataset.py
scNET/MultyGraphModel.py
scNET/Utils.py
scNET/__init__.py
scNET/coEmbeddedNetwork.py
scNET/main.py
scNET/Data/H_sapiens.net
scNET/Data/format_h_sapiens.csv
scNET/Data/readme
scNET/Data/scNET-env.yml
scNET/Embedding/readme
scNET/KNNs/readme
scNET/Models/readme
scnet-0.2.4.dist-info/LICENSE
scnet-0.2.4.dist-info/METADATA
scnet-0.2.4.dist-info/WHEEL
scnet-0.2.4.dist-info/top_level.txt
scnet-0.2.4.dist-info/RECORD
