Metadata-Version: 2.2
Name: scnet
Version: 0.2.4
Summary: Our method employs a unique dual-graph architecture based on graph neural networks (GNNs), enabling the joint representation of gene expression and PPI network data
Home-page: https://github.com/madilabcode/scNET
Author: Ron Sheinin
License-File: LICENSE
Requires-Dist: torch==2.6.0
Requires-Dist: torch-geometric==2.6.1
Requires-Dist: pandas>=2.2.1
Requires-Dist: numpy==1.26.4
Requires-Dist: networkx>=3.1
Requires-Dist: scanpy>=1.11.0
Requires-Dist: scikit-learn>=1.4.1
Requires-Dist: gseapy>=1.1.6
Requires-Dist: matplotlib>=3.8.0
Requires-Dist: igraph
Requires-Dist: leidenalg
Requires-Dist: tqdm
Dynamic: author
Dynamic: description
Dynamic: description-content-type
Dynamic: home-page
Dynamic: requires-dist
Dynamic: summary
